Metadata-Version: 2.1
Name: timefold-solver
Version: 1.10.0a0
Summary: An AI constraint solver that optimizes planning and scheduling problems
Home-page: https://github.com/TimefoldAI/timefold-solver-python
License: Apache License Version 2.0
Project-URL: Timefold Solver Documentation, https://timefold.ai/docs/timefold-solver/latest
Project-URL: Timefold Homepage, https://timefold.ai
Classifier: Development Status :: 1 - Planning
Classifier: Programming Language :: Python :: 3
Classifier: Topic :: Scientific/Engineering :: Artificial Intelligence
Classifier: Topic :: Software Development :: Libraries :: Java Libraries
Classifier: License :: OSI Approved :: Apache Software License
Classifier: Operating System :: OS Independent
Requires-Python: >=3.10
License-File: LICENSE.txt
Requires-Dist: JPype1 >=1.5.0
